README.txt
setup.cfg
setup.py
cenvars/__init__.py
cenvars/api.py
cenvars/cli.py
cenvars/codec.py
cenvars/constants.py
cenvars_client.egg-info/PKG-INFO
cenvars_client.egg-info/SOURCES.txt
cenvars_client.egg-info/dependency_links.txt
cenvars_client.egg-info/entry_points.txt
cenvars_client.egg-info/requires.txt
cenvars_client.egg-info/top_level.txt