Metadata-Version: 1.1
Name: cenvars-client
Version: 0.0.0.3
Summary: A Cenvars client and api library.
Home-page: https://bitbucket.org/hellwig/cenvars-client/
Author: Martin P. Hellwig
Author-email: martin.hellwig@gmail.com
License: BSD
Download-URL: https://bitbucket.org/hellwig/cenvars-client/get/2961ff615227eba6deef800dcf71936313c6190f.zip
Keywords: cenvars
Platform: UNKNOWN
Classifier: Programming Language :: Python :: 3
